arcane/mailer.py
arcane_mailer-0.2.4.dist-info/METADATA
arcane_mailer-0.2.4.dist-info/WHEEL
arcane_mailer-0.2.4.dist-info/RECORD
