Metadata-Version: 2.3
Name: arcane-mailer
Version: 0.2.4
Summary: Mail sender
Author: Arcane
Author-email: product@wearcane.com
Requires-Python: >=3.7,<4.0
Classifier: Programming Language :: Python :: 3
Classifier: Programming Language :: Python :: 3.7
Classifier: Programming Language :: Python :: 3.8
Classifier: Programming Language :: Python :: 3.9
Classifier: Programming Language :: Python :: 3.10
Classifier: Programming Language :: Python :: 3.11
Classifier: Programming Language :: Python :: 3.12
Classifier: Programming Language :: Python :: 3.13
Requires-Dist: mailjet_rest (>=1.3.0,<2.0.0)
Requires-Dist: typing-extensions (>=3.7)
